[
    {
        "name": "Castle Revert Class Menu",
        "trigger": null,
        "level_nid": "0",
        "condition": "True",
        "commands": [],
        "only_once": false,
        "priority": 20,
        "_source": [
            "choice;RevertChoice;Who to revert back to their base class?;Lord|{v:LordName},Player|{v:JagenName};EntryType=type_unit;backable",
            "if;v('RevertChoice') == 'Lord' and u('Lord').klass != 'Lord'",
            "  change_class;Lord;Lord;silent",
            "elif;v('RevertChoice') == 'Player' and u('Player').klass != 'Veteran'",
            "  change_class;Player;Veteran;silent",
            "elif;v('RevertChoice') != 'BACK'",
            "  sound;Error",
            "  alert;Already in base class!",
            "  trigger_script;0 Castle Revert Class Menu",
            "end",
            "if;v('RevertChoice') != 'BACK'",
            "  sound;Item",
            "  alert;Changed class back!",
            "end"
        ],
        "nid": "0 Castle Revert Class Menu"
    }
]