[
    {
        "nid": "Awakening",
        "name": "Awakening",
        "desc": "If unit is injured, grants +30 Hit/Avoid.",
        "icon_nid": "Skills_1",
        "icon_index": [
            13,
            37
        ],
        "components": [
            [
                "class_skill",
                null
            ],
            [
                "condition",
                "unit.get_hp() < unit.get_max_hp()"
            ],
            [
                "hit",
                30
            ],
            [
                "avoid",
                30
            ]
        ]
    }
]