[
    {
        "nid": "Dragon_Fang",
        "name": "Dragon Fang",
        "desc": "Proc: Skl/2%\nMultiplies damage dealt by 1.5x",
        "icon_nid": "Skills_1",
        "icon_index": [
            5,
            36
        ],
        "components": [
            [
                "class_skill",
                null
            ],
            [
                "attack_proc",
                "Dragon_Fang_Proc"
            ],
            [
                "proc_rate",
                "CRIT_HIT"
            ]
        ]
    }
]